census_shapefiles/__init__.py
census_shapefiles-1.1.2.dist-info/WHEEL
census_shapefiles-1.1.2.dist-info/METADATA
census_shapefiles-1.1.2.dist-info/RECORD
